srcomapipy/__init__.py
srcomapipy/srcomapipy.py
srcomapipy/srctypes.py
srcomapipy-0.5.5.dist-info/LICENSE
srcomapipy-0.5.5.dist-info/METADATA
srcomapipy-0.5.5.dist-info/WHEEL
srcomapipy-0.5.5.dist-info/top_level.txt
srcomapipy-0.5.5.dist-info/RECORD
