Metadata-Version: 2.1
Name: srcomapipy
Version: 0.5.5
Summary: python libray for the speedrun.com API
Home-page: https://github.com/Green-Bat/srcompy
Author: Green-Bat
License: MIT
Classifier: Programming Language :: Python :: 3.12
Classifier: License :: OSI Approved :: MIT License
Classifier: Operating System :: OS Independent
Requires-Python: >=3.10
License-File: LICENSE
Requires-Dist: requests>=2.23.3
